setup.py
twoLiquidMixingFlux/__init__.py
twoLiquidMixingFlux.egg-info/PKG-INFO
twoLiquidMixingFlux.egg-info/SOURCES.txt
twoLiquidMixingFlux.egg-info/dependency_links.txt
twoLiquidMixingFlux.egg-info/entry_points.txt
twoLiquidMixingFlux.egg-info/requires.txt
twoLiquidMixingFlux.egg-info/top_level.txt
twoLiquidMixingFlux.egg-info/zip-safe
twoLiquidMixingFlux/r1_7_1/__init__.py
twoLiquidMixingFlux/r2_0_0/__init__.py
twoLiquidMixingFlux/r2_1_0/__init__.py